{
  "urls": [
{"名称":"🥗饭太硬","网址":“http://www。饭太硬。com/tv“},
{"名称":"🔥凯速辛,"网址":“https://7587 . k store . space/Xin/Xin . JSON“},
{"名称":"🥗无意云","网址":“http://www.wya6.cn/tv/yc.php“},
{"名称":"🥗天微VIP ","网址":“https://gitee . com/tvkj/tw/raw/main/svip . JSON“},
{"名称":"🌸鑫影视","网址":“https://d . k store . space/download/8392/鑫影视/鑫视频。json “https://d.kstore.space/download/8392/xin video/xin video.json”},
{“姓名”:"🥗黄金影视",“URL”:WEB WEB WEB WEB WEB WEB WEB WEB WEB WEB WEB WEB WEB WEB WEB WEB WEB WEB WEB WEB WEB WEB WEB WEB WEB WEB WEB WEB WEB WEB WEB WEB WEB WEB WEB WEB},
{“姓名”:"🥗沉默在线",“URL”:“https://d.kstore.space/download/4203/9.json”},
{"名称":"🔥阿明“,"网址":“https://d . k store . space/download/7587/Amin . JSON“},
{"名称":"🍨4K线路","网址":“https://jihulab . com/ss 3234741/SJ/-/raw/875 bfc 142 a5 a3 b 202 B2C 232 ab 084 af 91076 b 0344/4k . JSON“},
{"名称":"🦅网游鹰","网址":“https://d . k store . space/download/5141/wyk . JSON“},
{"名称":“🈵cally满①","网址":“https://s2.pub/cally“},
{“姓名”:"🐝护法",“URL”:“https://pan.shangui.cc/f/w8NDhg/NkjAtL8C_0504hys.json”},
{“姓名”:"🐟摸鱼儿",“URL”:“WEB // 我不是. 触摸 Fisch.top”},
{“姓名”:"🐱清清摸鱼儿",“URL”:“http://clean.touch fish.top”},
{“姓名”:"💐金鑫影院",“URL”:WEB WEB WEB WEB WEB WEB WEB WEB WEB WEB WEB WEB WEB WEB WEB WEB WEB WEB WEB WEB WEB WEB WEB WEB WEB WEB WEB WEB WEB WEB WEB WEB WEB WEB WEB WEB WEB WEB WEB WEB WEB WEB WEB WEB WEB WEB WEB WEB WEB WEB WEB WEB WEB WEB WEB WEB WEB WEB WEB WEB WEB},
{"名称":"🎡西夏影视","网址":https://d . k存储。空间/下载/2912/0318。JSON“},
{"名称":"🐝神仙影视","网址":" http://www.liuyunw.com:88/img "},
{"名称":"🌹爱尚影视","网址":“https://gitee。com/海林886/fty/raw/master/电视盒子/爱尚。JSON“},
{"名称":"🪓恒星斧头帮","网址":" https://gitee . com/heng 546199810/hx VIP 8/raw/master/hx VIP 3 . txt "},
{"名称":"👶儿童专用","网址":" https://agit . ai/895322156/Q/raw/branch/master/TV/jy . txt "},
{"名称":"🍄挺好","网址":“http://ztha . top/TV box/thd JK . JSON“},
{"名称":"🌴多多影音","网址":“https://gitee . com/shangyunvip/shangyunvipdc/raw/master/多铎/dduo.json“},
{"名称":"🌍️鑫爷","网址":“https://d . k store . space/download/8392/鑫爺。json“},
{"名称":"🐰车妹妹","网址":“http://svip。微信。net:88/uploads/itvbox/svip。JSON“},
{"名称":"🕊️香佬在线","网址":" https://raw . git mirror . com/yw 88075/TV box/main/XYQTVBox/XYQTVBox . JSON "},
{"名称":"🐉小白龙","网址":《http://39.101.135.137:8080》},
{"名称"名称":"❤️爱心","网址":“https://admin . appto . cc/TV/TV box . JSON“},
{"名称":"🐈龙门","网址":“https://GH proxy . net/https://raw . githubusercontent . com/lm club/box/main/app/conf/TV . JSON“},
{“姓名”:"🐟摸鱼"，“网址”:“http://xn - ihqu10通信网络（Communicating Net的缩写）4许恩五4q818板英尺(board foot)34b.top/"},
{“姓名”:"🐞香雅情",“URL”:“https://github.moeyy.xyz/https://raw.githubusercontent.com/xyq254245/xynymlinerule/main/XYQTVBox.json”},
{“姓名”:"🍨小白线路",“URL”:“WEB // 白色.love”},
{“姓名”:"🐼肥猫线路",“URL”:WEB // 胖猫.live},
{“姓名”:"🌼菜妮丝线路",“URL”:“https://tvbox.cainisi.cf”},
{“姓名”:"☃️蚂蚁线路",“URL”:“https://la.kstore.space/download/2883/0110.txt”},
{“姓名”:"🅱️荷城茶秀",“URL”:“http://rihou.vip:88/Hollywood Tea Show”},
{“姓名”:"🦜云星线路",“URL”:“https://itvbox.cc/tvbox/Cloud Diary/1.m3u8”},
{“姓名”:"💦巧技线路",“URL”:“http://cdn.qiaoji8.com/tvbox.json”},
{“姓名”:"🔥骚零线路",“URL”:“https://100km.top/0”},
{“姓名”:更多信息 更多 about 线dxawi0,“URL”:“https://xhdwc.tk/0”},
{“姓名”:"📚少儿专线",“URL”:“http://122.51.37.23/man/shaoer.json”},
{“姓名”:"🏡潇洒线路",“URL”:“https://la.kstore.space/download/2863/01.txt”},
{“姓名”: "💫道长在线", “URL”: “https://pastebin.com/raw/5NHaxyGR”}
]c
